Metadata-Version: 2.1
Name: discconnect
Version: 0.5
Requires-Dist: requests>=2.25.1
